KS903_Ntural_Voice__AI_speech_sample_last/__init__.py
KS903NaturalIntonationAIVoice_Bate_vr_FinalLAST_librarypackages_datas-9.9.1.0.8.dist-info/METADATA
KS903NaturalIntonationAIVoice_Bate_vr_FinalLAST_librarypackages_datas-9.9.1.0.8.dist-info/WHEEL
KS903NaturalIntonationAIVoice_Bate_vr_FinalLAST_librarypackages_datas-9.9.1.0.8.dist-info/top_level.txt
KS903NaturalIntonationAIVoice_Bate_vr_FinalLAST_librarypackages_datas-9.9.1.0.8.dist-info/RECORD
