Metadata-Version: 2.1
Name: KS903NaturalIntonationAIVoice-Bate-vr-FinalLAST-librarypackages-datas
Version: 9.9.1.0.8
Summary: say's speech NaturalIntonation AI Voice library for KS903__Bate_vr_FinalLAST_librarypackages_datas__
Home-page: https://github.com/NPO_KS903_KATUYOSHI/say's_speech_NaturalIntonation_AI_Voice_library_for_KS903__Bate_vr_FinalLAST_librarypackages_datas__
Author: NPO_KS_903.lnc(President: Takeshi Kumura, Director: Takuma Ozawa)
Author-email: xksxkatuyoshi0009@gmail.com
License: MIT
Keywords: say's speech NaturalIntonation,AI_Sample_Bates_Voices_Base_library__Versions__Bate_vr_FinalLAST_librarypackages_datas__,for  KS903
Platform: UNKNOWN
Classifier: Development Status :: 3 - Alpha
Classifier: Intended Audience :: Developers
Classifier: License :: OSI Approved :: MIT License
Classifier: Programming Language :: Python :: 3
Classifier: Programming Language :: Python :: 3.8
Requires-Dist: pyttsx3
Requires-Dist: pandas
Requires-Dist: python-docx
Requires-Dist: PyPDF2
Requires-Dist: pillow
Requires-Dist: pytesseract
